{
  "timestamp": "2026-01-26T02:09:42.555Z",
  "geometry_sent": {
    "type": "Polygon",
    "coordinates": [
      [
        [
          5.124552999999992,
          7.304474
        ],
        [
          5.12522899999999,
          7.3054
        ],
        [
          5.126269999999977,
          7.30341
        ],
        [
          5.1252190000000155,
          7.302995
        ],
        [
          5.124552999999992,
          7.304474
        ]
      ]
    ]
  },
  "raw_api_response": {
    "data": [
      {
        "interval": {
          "from": "2025-07-26T01:09:40.842Z",
          "to": "2025-07-31T01:09:40.842Z"
        },
        "outputs": {
          "default": {
            "bands": {
              "B0": {
                "stats": {
                  "min": 0,
                  "max": 0,
                  "mean": 0,
                  "stDev": 0,
                  "sampleCount": 65536,
                  "noDataCount": 32214
                }
              },
              "B1": {
                "stats": {
                  "min": 0,
                  "max": 0,
                  "mean": 0,
                  "stDev": 0,
                  "sampleCount": 65536,
                  "noDataCount": 32214
                }
              }
            }
          }
        }
      },
      {
        "interval": {
          "from": "2025-07-31T01:09:40.842Z",
          "to": "2025-08-05T01:09:40.842Z"
        },
        "outputs": {
          "default": {
            "bands": {
              "B0": {
                "stats": {
                  "min": 0.008071748539805412,
                  "max": 0.023297490552067757,
                  "mean": 0.01780731445598744,
                  "stDev": 0.0020482841218229277,
                  "sampleCount": 65536,
                  "noDataCount": 32214
                }
              },
              "B1": {
                "stats": {
                  "min": 0.05589478462934494,
                  "max": 0.06911011040210724,
                  "mean": 0.06254374203313293,
                  "stDev": 0.0018493654768170407,
                  "sampleCount": 65536,
                  "noDataCount": 32214
                }
              }
            }
          }
        }
      },
      {
        "interval": {
          "from": "2025-08-05T01:09:40.842Z",
          "to": "2025-08-10T01:09:40.842Z"
        },
        "outputs": {
          "default": {
            "bands": {
              "B0": {
                "stats": {
                  "min": 0,
                  "max": 0.01703800819814205,
                  "mean": 0.005919811087461738,
                  "stDev": 0.0035518476177464494,
                  "sampleCount": 65536,
                  "noDataCount": 32214
                }
              },
              "B1": {
                "stats": {
                  "min": 0,
                  "max": 0,
                  "mean": 0,
                  "stDev": 0,
                  "sampleCount": 65536,
                  "noDataCount": 32214
                }
              }
            }
          }
        }
      },
      {
        "interval": {
          "from": "2025-08-10T01:09:40.842Z",
          "to": "2025-08-15T01:09:40.842Z"
        },
        "outputs": {
          "default": {
            "bands": {
              "B0": {
                "stats": {
                  "min": 0.013956310227513313,
                  "max": 0.061658840626478195,
                  "mean": 0.0425794003813065,
                  "stDev": 0.007843700358888261,
                  "sampleCount": 65536,
                  "noDataCount": 32214
                }
              },
              "B1": {
                "stats": {
                  "min": 0.01205902174115181,
                  "max": 0.09099038690328598,
                  "mean": 0.05163156714805291,
                  "stDev": 0.011498798985490206,
                  "sampleCount": 65536,
                  "noDataCount": 32214
                }
              }
            }
          }
        }
      },
      {
        "interval": {
          "from": "2025-08-15T01:09:40.842Z",
          "to": "2025-08-20T01:09:40.842Z"
        },
        "outputs": {
          "default": {
            "bands": {
              "B0": {
                "stats": {
                  "min": 0,
                  "max": 0.06987761706113815,
                  "mean": 0.02980203492127513,
                  "stDev": 0.012784222423299456,
                  "sampleCount": 65536,
                  "noDataCount": 32214
                }
              },
              "B1": {
                "stats": {
                  "min": 0,
                  "max": 0.035608310252428055,
                  "mean": 0.001439585197254784,
                  "stDev": 0.004893340181605377,
                  "sampleCount": 65536,
                  "noDataCount": 32214
                }
              }
            }
          }
        }
      },
      {
        "interval": {
          "from": "2025-08-20T01:09:40.842Z",
          "to": "2025-08-25T01:09:40.842Z"
        },
        "outputs": {
          "default": {
            "bands": {
              "B0": {
                "stats": {
                  "min": 0.08377425372600555,
                  "max": 0.12818096578121185,
                  "mean": 0.10131458911268201,
                  "stDev": 0.008261368406795514,
                  "sampleCount": 65536,
                  "noDataCount": 32214
                }
              },
              "B1": {
                "stats": {
                  "min": 0.07663551717996597,
                  "max": 0.13037480413913727,
                  "mean": 0.09823137750099756,
                  "stDev": 0.009323419523344256,
                  "sampleCount": 65536,
                  "noDataCount": 32214
                }
              }
            }
          }
        }
      },
      {
        "interval": {
          "from": "2025-08-25T01:09:40.842Z",
          "to": "2025-08-30T01:09:40.842Z"
        },
        "outputs": {
          "default": {
            "bands": {
              "B0": {
                "stats": {
                  "min": 0,
                  "max": 0.020727775990962982,
                  "mean": 0.0038862365976581287,
                  "stDev": 0.0048932459235452915,
                  "sampleCount": 65536,
                  "noDataCount": 32214
                }
              },
              "B1": {
                "stats": {
                  "min": 0,
                  "max": 0.04381963983178139,
                  "mean": 0.020422511440804716,
                  "stDev": 0.008577441851245886,
                  "sampleCount": 65536,
                  "noDataCount": 32214
                }
              }
            }
          }
        }
      },
      {
        "interval": {
          "from": "2025-08-30T01:09:40.842Z",
          "to": "2025-09-04T01:09:40.842Z"
        },
        "outputs": {
          "default": {
            "bands": {
              "B0": {
                "stats": {
                  "min": 0.0057208240032196045,
                  "max": 0.021412037312984467,
                  "mean": 0.012673351899045249,
                  "stDev": 0.002571990258982963,
                  "sampleCount": 65536,
                  "noDataCount": 32214
                }
              },
              "B1": {
                "stats": {
                  "min": 0.02240176312625408,
                  "max": 0.04162406921386719,
                  "mean": 0.029273593364843985,
                  "stDev": 0.002857184675563585,
                  "sampleCount": 65536,
                  "noDataCount": 32214
                }
              }
            }
          }
        }
      },
      {
        "interval": {
          "from": "2025-09-04T01:09:40.842Z",
          "to": "2025-09-09T01:09:40.842Z"
        },
        "outputs": {
          "default": {
            "bands": {
              "B0": {
                "stats": {
                  "min": 0.015285599045455456,
                  "max": 0.02609393745660782,
                  "mean": 0.019733919119243742,
                  "stDev": 0.0017817103528610673,
                  "sampleCount": 65536,
                  "noDataCount": 32214
                }
              },
              "B1": {
                "stats": {
                  "min": 0.017756255343556404,
                  "max": 0.02660909667611122,
                  "mean": 0.022030336459858493,
                  "stDev": 0.0015365029911600322,
                  "sampleCount": 65536,
                  "noDataCount": 32214
                }
              }
            }
          }
        }
      },
      {
        "interval": {
          "from": "2025-09-09T01:09:40.842Z",
          "to": "2025-09-14T01:09:40.842Z"
        },
        "outputs": {
          "default": {
            "bands": {
              "B0": {
                "stats": {
                  "min": 0,
                  "max": 0,
                  "mean": 0,
                  "stDev": 0,
                  "sampleCount": 65536,
                  "noDataCount": 32214
                }
              },
              "B1": {
                "stats": {
                  "min": 0,
                  "max": 0,
                  "mean": 0,
                  "stDev": 0,
                  "sampleCount": 65536,
                  "noDataCount": 32214
                }
              }
            }
          }
        }
      },
      {
        "interval": {
          "from": "2025-09-14T01:09:40.842Z",
          "to": "2025-09-19T01:09:40.842Z"
        },
        "outputs": {
          "default": {
            "bands": {
              "B0": {
                "stats": {
                  "min": 0.0064552342519164085,
                  "max": 0.020361991599202156,
                  "mean": 0.013494200392515853,
                  "stDev": 0.002795856975274648,
                  "sampleCount": 65536,
                  "noDataCount": 32214
                }
              },
              "B1": {
                "stats": {
                  "min": 0.03794369474053383,
                  "max": 0.055819738656282425,
                  "mean": 0.045631887873276746,
                  "stDev": 0.0029226222457822528,
                  "sampleCount": 65536,
                  "noDataCount": 32214
                }
              }
            }
          }
        }
      },
      {
        "interval": {
          "from": "2025-09-19T01:09:40.842Z",
          "to": "2025-09-24T01:09:40.842Z"
        },
        "outputs": {
          "default": {
            "bands": {
              "B0": {
                "stats": {
                  "min": 0.017683465033769608,
                  "max": 0.025956885889172554,
                  "mean": 0.021456626844908445,
                  "stDev": 0.001650244214771363,
                  "sampleCount": 65536,
                  "noDataCount": 32214
                }
              },
              "B1": {
                "stats": {
                  "min": 0.020768890157341957,
                  "max": 0.028264090418815613,
                  "mean": 0.024223216956288995,
                  "stDev": 0.0014846905200752213,
                  "sampleCount": 65536,
                  "noDataCount": 32214
                }
              }
            }
          }
        }
      },
      {
        "interval": {
          "from": "2025-09-24T01:09:40.842Z",
          "to": "2025-09-29T01:09:40.842Z"
        },
        "outputs": {
          "default": {
            "bands": {
              "B0": {
                "stats": {
                  "min": 0,
                  "max": 0,
                  "mean": 0,
                  "stDev": 0,
                  "sampleCount": 65536,
                  "noDataCount": 32214
                }
              },
              "B1": {
                "stats": {
                  "min": 0,
                  "max": 0,
                  "mean": 0,
                  "stDev": 0,
                  "sampleCount": 65536,
                  "noDataCount": 32214
                }
              }
            }
          }
        }
      },
      {
        "interval": {
          "from": "2025-09-29T01:09:40.842Z",
          "to": "2025-10-04T01:09:40.842Z"
        },
        "outputs": {
          "default": {
            "bands": {
              "B0": {
                "stats": {
                  "min": 0,
                  "max": 0,
                  "mean": 0,
                  "stDev": 0,
                  "sampleCount": 65536,
                  "noDataCount": 32214
                }
              },
              "B1": {
                "stats": {
                  "min": 0,
                  "max": 0,
                  "mean": 0,
                  "stDev": 0,
                  "sampleCount": 65536,
                  "noDataCount": 32214
                }
              }
            }
          }
        }
      },
      {
        "interval": {
          "from": "2025-10-04T01:09:40.842Z",
          "to": "2025-10-09T01:09:40.842Z"
        },
        "outputs": {
          "default": {
            "bands": {
              "B0": {
                "stats": {
                  "min": 0,
                  "max": 0.18887823820114136,
                  "mean": 0.053516312484122516,
                  "stDev": 0.042369913559978295,
                  "sampleCount": 65536,
                  "noDataCount": 32214
                }
              },
              "B1": {
                "stats": {
                  "min": 0,
                  "max": 0.12518788874149323,
                  "mean": 0.02032277585028036,
                  "stDev": 0.03021178700355674,
                  "sampleCount": 65536,
                  "noDataCount": 32214
                }
              }
            }
          }
        }
      },
      {
        "interval": {
          "from": "2025-10-09T01:09:40.842Z",
          "to": "2025-10-14T01:09:40.842Z"
        },
        "outputs": {
          "default": {
            "bands": {
              "B0": {
                "stats": {
                  "min": 0.21879449486732483,
                  "max": 0.8551453351974487,
                  "mean": 0.6745536872013359,
                  "stDev": 0.12938089017867188,
                  "sampleCount": 65536,
                  "noDataCount": 32214
                }
              },
              "B1": {
                "stats": {
                  "min": 0.11144773662090302,
                  "max": 0.5819966197013855,
                  "mean": 0.39861309208433127,
                  "stDev": 0.09802014349634909,
                  "sampleCount": 65536,
                  "noDataCount": 32214
                }
              }
            }
          }
        }
      },
      {
        "interval": {
          "from": "2025-10-14T01:09:40.842Z",
          "to": "2025-10-19T01:09:40.842Z"
        },
        "outputs": {
          "default": {
            "bands": {
              "B0": {
                "stats": {
                  "min": 0.2595190405845642,
                  "max": 0.8264768719673157,
                  "mean": 0.6916263048579484,
                  "stDev": 0.10171900931038179,
                  "sampleCount": 65536,
                  "noDataCount": 32214
                }
              },
              "B1": {
                "stats": {
                  "min": 0.1836158186197281,
                  "max": 0.5910161137580872,
                  "mean": 0.4528628716615466,
                  "stDev": 0.08108845447435822,
                  "sampleCount": 65536,
                  "noDataCount": 32214
                }
              }
            }
          }
        }
      },
      {
        "interval": {
          "from": "2025-10-19T01:09:40.842Z",
          "to": "2025-10-24T01:09:40.842Z"
        },
        "outputs": {
          "default": {
            "bands": {
              "B0": {
                "stats": {
                  "min": 0,
                  "max": 0,
                  "mean": 0,
                  "stDev": 0,
                  "sampleCount": 65536,
                  "noDataCount": 32214
                }
              },
              "B1": {
                "stats": {
                  "min": 0,
                  "max": 0,
                  "mean": 0,
                  "stDev": 0,
                  "sampleCount": 65536,
                  "noDataCount": 32214
                }
              }
            }
          }
        }
      },
      {
        "interval": {
          "from": "2025-10-24T01:09:40.842Z",
          "to": "2025-10-29T01:09:40.842Z"
        },
        "outputs": {
          "default": {
            "bands": {
              "B0": {
                "stats": {
                  "min": 0.03019213117659092,
                  "max": 0.03970789536833763,
                  "mean": 0.035271671944582667,
                  "stDev": 0.0016303157035364737,
                  "sampleCount": 65536,
                  "noDataCount": 32214
                }
              },
              "B1": {
                "stats": {
                  "min": 0.02381766401231289,
                  "max": 0.03322033956646919,
                  "mean": 0.027957092832820097,
                  "stDev": 0.0015441592373057415,
                  "sampleCount": 65536,
                  "noDataCount": 32214
                }
              }
            }
          }
        }
      },
      {
        "interval": {
          "from": "2025-10-29T01:09:40.842Z",
          "to": "2025-11-03T01:09:40.842Z"
        },
        "outputs": {
          "default": {
            "bands": {
              "B0": {
                "stats": {
                  "min": 0.37147215008735657,
                  "max": 0.7945131659507751,
                  "mean": 0.6459371168590073,
                  "stDev": 0.09326393650357692,
                  "sampleCount": 65536,
                  "noDataCount": 32214
                }
              },
              "B1": {
                "stats": {
                  "min": 0.22566446661949158,
                  "max": 0.5287116169929504,
                  "mean": 0.4031082267063196,
                  "stDev": 0.06390666865644745,
                  "sampleCount": 65536,
                  "noDataCount": 32214
                }
              }
            }
          }
        }
      },
      {
        "interval": {
          "from": "2025-11-03T01:09:40.842Z",
          "to": "2025-11-08T01:09:40.842Z"
        },
        "outputs": {
          "default": {
            "bands": {
              "B0": {
                "stats": {
                  "min": 0.26332709193229675,
                  "max": 0.5344171524047852,
                  "mean": 0.36099085593561986,
                  "stDev": 0.057103299242076216,
                  "sampleCount": 65536,
                  "noDataCount": 32214
                }
              },
              "B1": {
                "stats": {
                  "min": 0.15963302552700043,
                  "max": 0.38214969635009766,
                  "mean": 0.2520463205818087,
                  "stDev": 0.041792767376679335,
                  "sampleCount": 65536,
                  "noDataCount": 32214
                }
              }
            }
          }
        }
      },
      {
        "interval": {
          "from": "2025-11-08T01:09:40.842Z",
          "to": "2025-11-13T01:09:40.842Z"
        },
        "outputs": {
          "default": {
            "bands": {
              "B0": {
                "stats": {
                  "min": 0,
                  "max": 0.12013828754425049,
                  "mean": 0.032779077897457966,
                  "stDev": 0.035844388611381804,
                  "sampleCount": 65536,
                  "noDataCount": 32214
                }
              },
              "B1": {
                "stats": {
                  "min": 0,
                  "max": 0.08625592291355133,
                  "mean": 0.014092063598364795,
                  "stDev": 0.02071581558005378,
                  "sampleCount": 65536,
                  "noDataCount": 32214
                }
              }
            }
          }
        }
      },
      {
        "interval": {
          "from": "2025-11-13T01:09:40.842Z",
          "to": "2025-11-18T01:09:40.842Z"
        },
        "outputs": {
          "default": {
            "bands": {
              "B0": {
                "stats": {
                  "min": 0.4568420946598053,
                  "max": 0.7733230590820312,
                  "mean": 0.6852413165233746,
                  "stDev": 0.05549877167012901,
                  "sampleCount": 65536,
                  "noDataCount": 32214
                }
              },
              "B1": {
                "stats": {
                  "min": 0.298793762922287,
                  "max": 0.5502679347991943,
                  "mean": 0.45263485342978055,
                  "stDev": 0.04639543895678613,
                  "sampleCount": 65536,
                  "noDataCount": 32214
                }
              }
            }
          }
        }
      },
      {
        "interval": {
          "from": "2025-11-18T01:09:40.842Z",
          "to": "2025-11-23T01:09:40.842Z"
        },
        "outputs": {
          "default": {
            "bands": {
              "B0": {
                "stats": {
                  "min": 0.46507352590560913,
                  "max": 0.7903186678886414,
                  "mean": 0.6995598840174033,
                  "stDev": 0.05399149020846054,
                  "sampleCount": 65536,
                  "noDataCount": 32214
                }
              },
              "B1": {
                "stats": {
                  "min": 0.33918386697769165,
                  "max": 0.5756797194480896,
                  "mean": 0.47670496356625963,
                  "stDev": 0.04150624652530004,
                  "sampleCount": 65536,
                  "noDataCount": 32214
                }
              }
            }
          }
        }
      },
      {
        "interval": {
          "from": "2025-11-23T01:09:40.842Z",
          "to": "2025-11-28T01:09:40.842Z"
        },
        "outputs": {
          "default": {
            "bands": {
              "B0": {
                "stats": {
                  "min": 0.5202822089195251,
                  "max": 0.7819104194641113,
                  "mean": 0.6982398144437937,
                  "stDev": 0.049601300857153065,
                  "sampleCount": 65536,
                  "noDataCount": 32214
                }
              },
              "B1": {
                "stats": {
                  "min": 0.30057087540626526,
                  "max": 0.5532293319702148,
                  "mean": 0.4498824356008094,
                  "stDev": 0.03928425143871957,
                  "sampleCount": 65536,
                  "noDataCount": 32214
                }
              }
            }
          }
        }
      },
      {
        "interval": {
          "from": "2025-11-28T01:09:40.842Z",
          "to": "2025-12-03T01:09:40.842Z"
        },
        "outputs": {
          "default": {
            "bands": {
              "B0": {
                "stats": {
                  "min": 0.4260709285736084,
                  "max": 0.6269662976264954,
                  "mean": 0.5453671720693894,
                  "stDev": 0.03394488232904011,
                  "sampleCount": 65536,
                  "noDataCount": 32214
                }
              },
              "B1": {
                "stats": {
                  "min": 0.23578497767448425,
                  "max": 0.414760023355484,
                  "mean": 0.34162023846330586,
                  "stDev": 0.027067762715977373,
                  "sampleCount": 65536,
                  "noDataCount": 32214
                }
              }
            }
          }
        }
      },
      {
        "interval": {
          "from": "2025-12-03T01:09:40.842Z",
          "to": "2025-12-08T01:09:40.842Z"
        },
        "outputs": {
          "default": {
            "bands": {
              "B0": {
                "stats": {
                  "min": 0.32691535353660583,
                  "max": 0.563086986541748,
                  "mean": 0.4736961477530184,
                  "stDev": 0.04148119148637403,
                  "sampleCount": 65536,
                  "noDataCount": 32214
                }
              },
              "B1": {
                "stats": {
                  "min": 0.1955186128616333,
                  "max": 0.40281587839126587,
                  "mean": 0.2993395370441037,
                  "stDev": 0.03322620013304495,
                  "sampleCount": 65536,
                  "noDataCount": 32214
                }
              }
            }
          }
        }
      },
      {
        "interval": {
          "from": "2025-12-08T01:09:40.842Z",
          "to": "2025-12-13T01:09:40.842Z"
        },
        "outputs": {
          "default": {
            "bands": {
              "B0": {
                "stats": {
                  "min": 0.128305584192276,
                  "max": 0.41092392802238464,
                  "mean": 0.31117912455270863,
                  "stDev": 0.035306041327141234,
                  "sampleCount": 65536,
                  "noDataCount": 32214
                }
              },
              "B1": {
                "stats": {
                  "min": 0.021790998056530952,
                  "max": 0.3007058799266815,
                  "mean": 0.20554964411132842,
                  "stDev": 0.03175428258861566,
                  "sampleCount": 65536,
                  "noDataCount": 32214
                }
              }
            }
          }
        }
      },
      {
        "interval": {
          "from": "2025-12-13T01:09:40.842Z",
          "to": "2025-12-18T01:09:40.842Z"
        },
        "outputs": {
          "default": {
            "bands": {
              "B0": {
                "stats": {
                  "min": 0.46666666865348816,
                  "max": 0.7014859318733215,
                  "mean": 0.5921971690502027,
                  "stDev": 0.036946763312026044,
                  "sampleCount": 65536,
                  "noDataCount": 32214
                }
              },
              "B1": {
                "stats": {
                  "min": 0.30010277032852173,
                  "max": 0.49112918972969055,
                  "mean": 0.3841293077647811,
                  "stDev": 0.03141474357875248,
                  "sampleCount": 65536,
                  "noDataCount": 32214
                }
              }
            }
          }
        }
      },
      {
        "interval": {
          "from": "2025-12-18T01:09:40.842Z",
          "to": "2025-12-23T01:09:40.842Z"
        },
        "outputs": {
          "default": {
            "bands": {
              "B0": {
                "stats": {
                  "min": 0,
                  "max": 0.24082639813423157,
                  "mean": 0.05247719261080597,
                  "stDev": 0.06146308199582473,
                  "sampleCount": 65536,
                  "noDataCount": 32214
                }
              },
              "B1": {
                "stats": {
                  "min": 0,
                  "max": 0.2331382781267166,
                  "mean": 0.026443866248989152,
                  "stDev": 0.04327839380095026,
                  "sampleCount": 65536,
                  "noDataCount": 32214
                }
              }
            }
          }
        }
      },
      {
        "interval": {
          "from": "2025-12-23T01:09:40.842Z",
          "to": "2025-12-28T01:09:40.842Z"
        },
        "outputs": {
          "default": {
            "bands": {
              "B0": {
                "stats": {
                  "min": 0.38003137707710266,
                  "max": 0.6062581539154053,
                  "mean": 0.4773779310262339,
                  "stDev": 0.03885371325958936,
                  "sampleCount": 65536,
                  "noDataCount": 32214
                }
              },
              "B1": {
                "stats": {
                  "min": 0.2176283448934555,
                  "max": 0.41584157943725586,
                  "mean": 0.3018117830855758,
                  "stDev": 0.03436155340277584,
                  "sampleCount": 65536,
                  "noDataCount": 32214
                }
              }
            }
          }
        }
      },
      {
        "interval": {
          "from": "2025-12-28T01:09:40.842Z",
          "to": "2026-01-02T01:09:40.842Z"
        },
        "outputs": {
          "default": {
            "bands": {
              "B0": {
                "stats": {
                  "min": 0.2375948578119278,
                  "max": 0.5136690735816956,
                  "mean": 0.34212674785276437,
                  "stDev": 0.05406434858530962,
                  "sampleCount": 65536,
                  "noDataCount": 32214
                }
              },
              "B1": {
                "stats": {
                  "min": 0.10043668001890182,
                  "max": 0.3432266414165497,
                  "mean": 0.20419688128732358,
                  "stDev": 0.03916931152718882,
                  "sampleCount": 65536,
                  "noDataCount": 32214
                }
              }
            }
          }
        }
      },
      {
        "interval": {
          "from": "2026-01-02T01:09:40.842Z",
          "to": "2026-01-07T01:09:40.842Z"
        },
        "outputs": {
          "default": {
            "bands": {
              "B0": {
                "stats": {
                  "min": 0.39156627655029297,
                  "max": 0.644537091255188,
                  "mean": 0.4914139491474551,
                  "stDev": 0.04648291108353821,
                  "sampleCount": 65536,
                  "noDataCount": 32214
                }
              },
              "B1": {
                "stats": {
                  "min": 0.22162161767482758,
                  "max": 0.4472098648548126,
                  "mean": 0.30012389672504797,
                  "stDev": 0.03600500977419859,
                  "sampleCount": 65536,
                  "noDataCount": 32214
                }
              }
            }
          }
        }
      },
      {
        "interval": {
          "from": "2026-01-07T01:09:40.842Z",
          "to": "2026-01-12T01:09:40.842Z"
        },
        "outputs": {
          "default": {
            "bands": {
              "B0": {
                "stats": {
                  "min": 0.15499825775623322,
                  "max": 0.2617627680301666,
                  "mean": 0.20338650886969997,
                  "stDev": 0.018621445122241537,
                  "sampleCount": 65536,
                  "noDataCount": 32214
                }
              },
              "B1": {
                "stats": {
                  "min": 0.08617234230041504,
                  "max": 0.1731361746788025,
                  "mean": 0.1306691994165784,
                  "stDev": 0.01741627807018497,
                  "sampleCount": 65536,
                  "noDataCount": 32214
                }
              }
            }
          }
        }
      },
      {
        "interval": {
          "from": "2026-01-12T01:09:40.842Z",
          "to": "2026-01-17T01:09:40.842Z"
        },
        "outputs": {
          "default": {
            "bands": {
              "B0": {
                "stats": {
                  "min": 0.3465665280818939,
                  "max": 0.48827293515205383,
                  "mean": 0.3896403912360707,
                  "stDev": 0.025342224086645375,
                  "sampleCount": 65536,
                  "noDataCount": 32214
                }
              },
              "B1": {
                "stats": {
                  "min": 0.1965988129377365,
                  "max": 0.3230912387371063,
                  "mean": 0.23629979025282993,
                  "stDev": 0.019378965009490903,
                  "sampleCount": 65536,
                  "noDataCount": 32214
                }
              }
            }
          }
        }
      },
      {
        "interval": {
          "from": "2026-01-17T01:09:40.842Z",
          "to": "2026-01-22T01:09:40.842Z"
        },
        "outputs": {
          "default": {
            "bands": {
              "B0": {
                "stats": {
                  "min": 0.35227271914482117,
                  "max": 0.5549065470695496,
                  "mean": 0.4193806241645261,
                  "stDev": 0.03603655041340565,
                  "sampleCount": 65536,
                  "noDataCount": 32214
                }
              },
              "B1": {
                "stats": {
                  "min": 0.17496152222156525,
                  "max": 0.35024094581604004,
                  "mean": 0.2419533655516946,
                  "stDev": 0.02373923433039236,
                  "sampleCount": 65536,
                  "noDataCount": 32214
                }
              }
            }
          }
        }
      }
    ],
    "status": "OK"
  }
}